pysto/__init__.py
pysto/imgproc.py
pysto/imgprocITK.py
pysto-1.4.1.dist-info/DESCRIPTION.rst
pysto-1.4.1.dist-info/METADATA
pysto-1.4.1.dist-info/RECORD
pysto-1.4.1.dist-info/WHEEL
pysto-1.4.1.dist-info/metadata.json
pysto-1.4.1.dist-info/top_level.txt
